[
  {
    "datasetId": "ds-farmers-25-ws",
    "portname": "09302023",
    "sourceServerName": "BERMUDA-SQL01",
    "sourceDatabaseName": "Re_BER_25_Farmers_WS_EDM_01",
    "sourceTableName": "Re_BER_25_Farmers_WS_EDM_01__EVOLUTION",
    "aggregation": "COUNTRY",
    "geographyLevel": "COUNTRY",
    "country": "US",
    "countryName": "United States",
    "geographyId": "US",
    "peril": "WS",
    "occupancy": "Permanent",
    "occupancyGroup": "Res-MFD",
    "occupancySegment": "RESIDENTIAL",
    "construction": "Masonry",
    "yearBuilt": "1980 to 2000",
    "distanceToCoast": "e=> 2.0 - 5 Miles from Coast",
    "geocodingQuality": "Coordinate",
    "numberOfStories": "1-3 stories",
    "building": 14700000000.0,
    "contents": 7350000000.0,
    "bi": 2450000000.0,
    "tiv": 24500000000,
    "explimGross": 19600000000.0,
    "explimNet": 14700000000.0,
    "locationCount": 70000,
    "accountCount": 5384,
    "invalidTiv": 12250000.0,
    "invalidCount": 140,
    "currency": "USD",
    "exposureDataCutoffDate": "2023-09-30T00:00:00Z"
  },
  {
    "datasetId": "ds-farmers-25-ws",
    "portname": "09302023",
    "sourceServerName": "BERMUDA-SQL01",
    "sourceDatabaseName": "Re_BER_25_Farmers_WS_EDM_01",
    "sourceTableName": "Re_BER_25_Farmers_WS_EDM_01__EVOLUTION",
    "aggregation": "STATE",
    "geographyLevel": "STATE",
    "country": "US",
    "countryName": "United States",
    "geographyId": "US-FL",
    "peril": "WS",
    "occupancy": "Permanent",
    "occupancyGroup": "Res-MFD",
    "occupancySegment": "RESIDENTIAL",
    "construction": "Reinforced",
    "yearBuilt": "1960 to 1980",
    "distanceToCoast": "c=> 0.5 - 1 Miles from Coast",
    "geocodingQuality": "Coordinate",
    "numberOfStories": "1-3 stories",
    "building": 5880000000.0,
    "contents": 2940000000.0,
    "bi": 980000000.0,
    "tiv": 9800000000,
    "explimGross": 7840000000.0,
    "explimNet": 5880000000.0,
    "locationCount": 28000,
    "accountCount": 2153,
    "invalidTiv": null,
    "invalidCount": null,
    "currency": "USD",
    "exposureDataCutoffDate": "2023-09-30T00:00:00Z",
    "statecode": "FL",
    "stateName": "FLORIDA"
  },
  {
    "datasetId": "ds-farmers-25-ws",
    "portname": "09302023",
    "sourceServerName": "BERMUDA-SQL01",
    "sourceDatabaseName": "Re_BER_25_Farmers_WS_EDM_01",
    "sourceTableName": "Re_BER_25_Farmers_WS_EDM_01__EVOLUTION",
    "aggregation": "STATE",
    "geographyLevel": "STATE",
    "country": "US",
    "countryName": "United States",
    "geographyId": "US-TX",
    "peril": "WS",
    "occupancy": "Permanent",
    "occupancyGroup": "Res-SFD",
    "occupancySegment": "RESIDENTIAL",
    "construction": "Wood",
    "yearBuilt": "1980 to 2000",
    "distanceToCoast": "d=> 1.0 - 2 Miles from Coast",
    "geocodingQuality": "Street/Parcel",
    "numberOfStories": "4-7 stories",
    "building": 2160000000.0,
    "contents": 1080000000.0,
    "bi": 360000000.0,
    "tiv": 3600000000,
    "explimGross": 2880000000.0,
    "explimNet": 2160000000.0,
    "locationCount": 10285,
    "accountCount": 791,
    "invalidTiv": null,
    "invalidCount": null,
    "currency": "USD",
    "exposureDataCutoffDate": "2023-09-30T00:00:00Z",
    "statecode": "TX",
    "stateName": "TEXAS"
  },
  {
    "datasetId": "ds-farmers-25-ws",
    "portname": "09302023",
    "sourceServerName": "BERMUDA-SQL01",
    "sourceDatabaseName": "Re_BER_25_Farmers_WS_EDM_01",
    "sourceTableName": "Re_BER_25_Farmers_WS_EDM_01__EVOLUTION",
    "aggregation": "STATE",
    "geographyLevel": "STATE",
    "country": "US",
    "countryName": "United States",
    "geographyId": "US-LA",
    "peril": "WS",
    "occupancy": "Permanent",
    "occupancyGroup": "Com-Office",
    "occupancySegment": "COMMERCIAL",
    "construction": "Steel",
    "yearBuilt": "2000 to Present",
    "distanceToCoast": "e=> 2.0 - 5 Miles from Coast",
    "geocodingQuality": "Postal code",
    "numberOfStories": "8+ stories",
    "building": 1140000000.0,
    "contents": 570000000.0,
    "bi": 190000000.0,
    "tiv": 1900000000,
    "explimGross": 1520000000.0,
    "explimNet": 1140000000.0,
    "locationCount": 5428,
    "accountCount": 417,
    "invalidTiv": null,
    "invalidCount": null,
    "currency": "USD",
    "exposureDataCutoffDate": "2023-09-30T00:00:00Z",
    "statecode": "LA",
    "stateName": "LOUISIANA"
  },
  {
    "datasetId": "ds-farmers-25-ws",
    "portname": "09302023",
    "sourceServerName": "BERMUDA-SQL01",
    "sourceDatabaseName": "Re_BER_25_Farmers_WS_EDM_01",
    "sourceTableName": "Re_BER_25_Farmers_WS_EDM_01__EVOLUTION",
    "aggregation": "STATE",
    "geographyLevel": "STATE",
    "country": "US",
    "countryName": "United States",
    "geographyId": "US-NC",
    "peril": "WS",
    "occupancy": "Permanent",
    "occupancyGroup": "Com-Retail",
    "occupancySegment": "COMMERCIAL",
    "construction": "Masonry",
    "yearBuilt": "Unknown",
    "distanceToCoast": "f=> 5.0 - 10 Miles from Coast",
    "geocodingQuality": "Block Group",
    "numberOfStories": "(blank)",
    "building": 840000000.0,
    "contents": 420000000.0,
    "bi": 140000000.0,
    "tiv": 1400000000,
    "explimGross": 1120000000.0,
    "explimNet": 840000000.0,
    "locationCount": 4000,
    "accountCount": 307,
    "invalidTiv": null,
    "invalidCount": null,
    "currency": "USD",
    "exposureDataCutoffDate": "2023-09-30T00:00:00Z",
    "statecode": "NC",
    "stateName": "NORTH CAROLINA"
  },
  {
    "datasetId": "ds-farmers-25-ws",
    "portname": "09302023",
    "sourceServerName": "BERMUDA-SQL01",
    "sourceDatabaseName": "Re_BER_25_Farmers_WS_EDM_01",
    "sourceTableName": "Re_BER_25_Farmers_WS_EDM_01__EVOLUTION",
    "aggregation": "STATE",
    "geographyLevel": "STATE",
    "country": "US",
    "countryName": "United States",
    "geographyId": "US-SC",
    "peril": "WS",
    "occupancy": "Permanent",
    "occupancyGroup": "Ind-Light",
    "occupancySegment": "INDUSTRIAL",
    "construction": "Reinforced",
    "yearBuilt": "1930 to 1960",
    "distanceToCoast": "g=> +10 Miles from Coast",
    "geocodingQuality": "Coordinate",
    "numberOfStories": "1-3 stories",
    "building": 570000000.0,
    "contents": 285000000.0,
    "bi": 95000000.0,
    "tiv": 950000000,
    "explimGross": 760000000.0,
    "explimNet": 570000000.0,
    "locationCount": 2714,
    "accountCount": 208,
    "invalidTiv": null,
    "invalidCount": null,
    "currency": "USD",
    "exposureDataCutoffDate": "2023-09-30T00:00:00Z",
    "statecode": "SC",
    "stateName": "SOUTH CAROLINA"
  },
  {
    "datasetId": "ds-farmers-25-ws",
    "portname": "09302023",
    "sourceServerName": "BERMUDA-SQL01",
    "sourceDatabaseName": "Re_BER_25_Farmers_WS_EDM_01",
    "sourceTableName": "Re_BER_25_Farmers_WS_EDM_01__EVOLUTION",
    "aggregation": "STATE",
    "geographyLevel": "STATE",
    "country": "US",
    "countryName": "United States",
    "geographyId": "US-CA",
    "peril": "WS",
    "occupancy": "Permanent",
    "occupancyGroup": "Ind-Heavy",
    "occupancySegment": "INDUSTRIAL",
    "construction": "Wood",
    "yearBuilt": "1960 to 1980",
    "distanceToCoast": "a=> At the Coast",
    "geocodingQuality": "Street/Parcel",
    "numberOfStories": "4-7 stories",
    "building": 1440000000.0,
    "contents": 720000000.0,
    "bi": 240000000.0,
    "tiv": 2400000000,
    "explimGross": 1920000000.0,
    "explimNet": 1440000000.0,
    "locationCount": 6857,
    "accountCount": 527,
    "invalidTiv": null,
    "invalidCount": null,
    "currency": "USD",
    "exposureDataCutoffDate": "2023-09-30T00:00:00Z",
    "statecode": "CA",
    "stateName": "CALIFORNIA"
  },
  {
    "datasetId": "ds-farmers-25-ws",
    "portname": "09302023",
    "sourceServerName": "BERMUDA-SQL01",
    "sourceDatabaseName": "Re_BER_25_Farmers_WS_EDM_01",
    "sourceTableName": "Re_BER_25_Farmers_WS_EDM_01__EVOLUTION",
    "aggregation": "STATE",
    "geographyLevel": "STATE",
    "country": "US",
    "countryName": "United States",
    "geographyId": "US-NY",
    "peril": "WS",
    "occupancy": "Permanent",
    "occupancyGroup": "Res-MFD",
    "occupancySegment": "RESIDENTIAL",
    "construction": "Steel",
    "yearBuilt": "1980 to 2000",
    "distanceToCoast": "b=> 0 - 0.5 Miles from Coast",
    "geocodingQuality": "Postal code",
    "numberOfStories": "8+ stories",
    "building": 432000000.0,
    "contents": 216000000.0,
    "bi": 72000000.0,
    "tiv": 720000000,
    "explimGross": 576000000.0,
    "explimNet": 432000000.0,
    "locationCount": 2057,
    "accountCount": 158,
    "invalidTiv": null,
    "invalidCount": null,
    "currency": "USD",
    "exposureDataCutoffDate": "2023-09-30T00:00:00Z",
    "statecode": "NY",
    "stateName": "NEW YORK"
  },
  {
    "datasetId": "ds-farmers-25-ws",
    "portname": "09302023",
    "sourceServerName": "BERMUDA-SQL01",
    "sourceDatabaseName": "Re_BER_25_Farmers_WS_EDM_01",
    "sourceTableName": "Re_BER_25_Farmers_WS_EDM_01__EVOLUTION",
    "aggregation": "COUNTY",
    "geographyLevel": "COUNTY",
    "country": "US",
    "countryName": "United States",
    "geographyId": "US-FL-12086",
    "peril": "WS",
    "occupancy": "Permanent",
    "occupancyGroup": "Com-Office",
    "occupancySegment": "COMMERCIAL",
    "construction": "Masonry",
    "yearBuilt": "1980 to 2000",
    "distanceToCoast": "b=> 0 - 0.5 Miles from Coast",
    "geocodingQuality": "Street/Parcel",
    "numberOfStories": "8+ stories",
    "building": 2640000000.0,
    "contents": 1320000000.0,
    "bi": 440000000.0,
    "tiv": 4400000000,
    "explimGross": 3520000000.0,
    "explimNet": 2640000000.0,
    "locationCount": 15714,
    "accountCount": 1208,
    "invalidTiv": null,
    "invalidCount": null,
    "currency": "USD",
    "exposureDataCutoffDate": "2023-09-30T00:00:00Z",
    "statecode": "FL",
    "stateName": "FLORIDA",
    "county": "12086",
    "countyName": "Miami-Dade"
  },
  {
    "datasetId": "ds-farmers-25-ws",
    "portname": "09302023",
    "sourceServerName": "BERMUDA-SQL01",
    "sourceDatabaseName": "Re_BER_25_Farmers_WS_EDM_01",
    "sourceTableName": "Re_BER_25_Farmers_WS_EDM_01__EVOLUTION",
    "aggregation": "COUNTY",
    "geographyLevel": "COUNTY",
    "country": "US",
    "countryName": "United States",
    "geographyId": "US-FL-12011",
    "peril": "WS",
    "occupancy": "Permanent",
    "occupancyGroup": "Com-Retail",
    "occupancySegment": "COMMERCIAL",
    "construction": "Reinforced",
    "yearBuilt": "2000 to Present",
    "distanceToCoast": "c=> 0.5 - 1 Miles from Coast",
    "geocodingQuality": "Postal code",
    "numberOfStories": "(blank)",
    "building": 1740000000.0,
    "contents": 870000000.0,
    "bi": 290000000.0,
    "tiv": 2900000000,
    "explimGross": 2320000000.0,
    "explimNet": 1740000000.0,
    "locationCount": 10357,
    "accountCount": 796,
    "invalidTiv": null,
    "invalidCount": null,
    "currency": "USD",
    "exposureDataCutoffDate": "2023-09-30T00:00:00Z",
    "statecode": "FL",
    "stateName": "FLORIDA",
    "county": "12011",
    "countyName": "Broward"
  },
  {
    "datasetId": "ds-farmers-25-ws",
    "portname": "09302023",
    "sourceServerName": "BERMUDA-SQL01",
    "sourceDatabaseName": "Re_BER_25_Farmers_WS_EDM_01",
    "sourceTableName": "Re_BER_25_Farmers_WS_EDM_01__EVOLUTION",
    "aggregation": "COUNTY",
    "geographyLevel": "COUNTY",
    "country": "US",
    "countryName": "United States",
    "geographyId": "US-TX-48201",
    "peril": "WS",
    "occupancy": "Permanent",
    "occupancyGroup": "Ind-Light",
    "occupancySegment": "INDUSTRIAL",
    "construction": "Wood",
    "yearBuilt": "Unknown",
    "distanceToCoast": "d=> 1.0 - 2 Miles from Coast",
    "geocodingQuality": "Block Group",
    "numberOfStories": "1-3 stories",
    "building": 1140000000.0,
    "contents": 570000000.0,
    "bi": 190000000.0,
    "tiv": 1900000000,
    "explimGross": 1520000000.0,
    "explimNet": 1140000000.0,
    "locationCount": 6785,
    "accountCount": 521,
    "invalidTiv": null,
    "invalidCount": null,
    "currency": "USD",
    "exposureDataCutoffDate": "2023-09-30T00:00:00Z",
    "statecode": "TX",
    "stateName": "TEXAS",
    "county": "48201",
    "countyName": "Harris"
  },
  {
    "datasetId": "ds-farmers-25-ws",
    "portname": "09302023",
    "sourceServerName": "BERMUDA-SQL01",
    "sourceDatabaseName": "Re_BER_25_Farmers_WS_EDM_01",
    "sourceTableName": "Re_BER_25_Farmers_WS_EDM_01__EVOLUTION",
    "aggregation": "COUNTY",
    "geographyLevel": "COUNTY",
    "country": "US",
    "countryName": "United States",
    "geographyId": "US-LA-22071",
    "peril": "WS",
    "occupancy": "Permanent",
    "occupancyGroup": "Ind-Heavy",
    "occupancySegment": "INDUSTRIAL",
    "construction": "Steel",
    "yearBuilt": "1930 to 1960",
    "distanceToCoast": "e=> 2.0 - 5 Miles from Coast",
    "geocodingQuality": "Coordinate",
    "numberOfStories": "4-7 stories",
    "building": 720000000.0,
    "contents": 360000000.0,
    "bi": 120000000.0,
    "tiv": 1200000000,
    "explimGross": 960000000.0,
    "explimNet": 720000000.0,
    "locationCount": 4285,
    "accountCount": 329,
    "invalidTiv": null,
    "invalidCount": null,
    "currency": "USD",
    "exposureDataCutoffDate": "2023-09-30T00:00:00Z",
    "statecode": "LA",
    "stateName": "LOUISIANA",
    "county": "22071",
    "countyName": "Orleans"
  },
  {
    "datasetId": "ds-farmers-25-ws",
    "portname": "09302023",
    "sourceServerName": "BERMUDA-SQL01",
    "sourceDatabaseName": "Re_BER_25_Farmers_WS_EDM_01",
    "sourceTableName": "Re_BER_25_Farmers_WS_EDM_01__EVOLUTION",
    "aggregation": "COUNTY",
    "geographyLevel": "COUNTY",
    "country": "US",
    "countryName": "United States",
    "geographyId": "US-NC-37119",
    "peril": "WS",
    "occupancy": "Permanent",
    "occupancyGroup": "Res-MFD",
    "occupancySegment": "RESIDENTIAL",
    "construction": "Masonry",
    "yearBuilt": "1960 to 1980",
    "distanceToCoast": "f=> 5.0 - 10 Miles from Coast",
    "geocodingQuality": "Street/Parcel",
    "numberOfStories": "8+ stories",
    "building": 420000000.0,
    "contents": 210000000.0,
    "bi": 70000000.0,
    "tiv": 700000000,
    "explimGross": 560000000.0,
    "explimNet": 420000000.0,
    "locationCount": 2500,
    "accountCount": 192,
    "invalidTiv": null,
    "invalidCount": null,
    "currency": "USD",
    "exposureDataCutoffDate": "2023-09-30T00:00:00Z",
    "statecode": "NC",
    "stateName": "NORTH CAROLINA",
    "county": "37119",
    "countyName": "Mecklenburg"
  },
  {
    "datasetId": "ds-farmers-25-ws",
    "portname": "09302023",
    "sourceServerName": "BERMUDA-SQL01",
    "sourceDatabaseName": "Re_BER_25_Farmers_WS_EDM_01",
    "sourceTableName": "Re_BER_25_Farmers_WS_EDM_01__EVOLUTION",
    "aggregation": "COUNTY",
    "geographyLevel": "COUNTY",
    "country": "US",
    "countryName": "United States",
    "geographyId": "US-SC-45019",
    "peril": "WS",
    "occupancy": "Permanent",
    "occupancyGroup": "Res-SFD",
    "occupancySegment": "RESIDENTIAL",
    "construction": "Reinforced",
    "yearBuilt": "1980 to 2000",
    "distanceToCoast": "g=> +10 Miles from Coast",
    "geocodingQuality": "Postal code",
    "numberOfStories": "(blank)",
    "building": 288000000.0,
    "contents": 144000000.0,
    "bi": 48000000.0,
    "tiv": 480000000,
    "explimGross": 384000000.0,
    "explimNet": 288000000.0,
    "locationCount": 1714,
    "accountCount": 131,
    "invalidTiv": null,
    "invalidCount": null,
    "currency": "USD",
    "exposureDataCutoffDate": "2023-09-30T00:00:00Z",
    "statecode": "SC",
    "stateName": "SOUTH CAROLINA",
    "county": "45019",
    "countyName": "Charleston"
  },
  {
    "datasetId": "ds-farmers-25-ws",
    "portname": "09302023",
    "sourceServerName": "BERMUDA-SQL01",
    "sourceDatabaseName": "Re_BER_25_Farmers_WS_EDM_01",
    "sourceTableName": "Re_BER_25_Farmers_WS_EDM_01__EVOLUTION",
    "aggregation": "COUNTY",
    "geographyLevel": "COUNTY",
    "country": "US",
    "countryName": "United States",
    "geographyId": "US-CA-06037",
    "peril": "WS",
    "occupancy": "Permanent",
    "occupancyGroup": "Com-Office",
    "occupancySegment": "COMMERCIAL",
    "construction": "Wood",
    "yearBuilt": "2000 to Present",
    "distanceToCoast": "a=> At the Coast",
    "geocodingQuality": "Block Group",
    "numberOfStories": "1-3 stories",
    "building": 780000000.0,
    "contents": 390000000.0,
    "bi": 130000000.0,
    "tiv": 1300000000,
    "explimGross": 1040000000.0,
    "explimNet": 780000000.0,
    "locationCount": 4642,
    "accountCount": 357,
    "invalidTiv": null,
    "invalidCount": null,
    "currency": "USD",
    "exposureDataCutoffDate": "2023-09-30T00:00:00Z",
    "statecode": "CA",
    "stateName": "CALIFORNIA",
    "county": "06037",
    "countyName": "Los Angeles"
  },
  {
    "datasetId": "ds-farmers-25-ws",
    "portname": "09302023",
    "sourceServerName": "BERMUDA-SQL01",
    "sourceDatabaseName": "Re_BER_25_Farmers_WS_EDM_01",
    "sourceTableName": "Re_BER_25_Farmers_WS_EDM_01__EVOLUTION",
    "aggregation": "COUNTY",
    "geographyLevel": "COUNTY",
    "country": "US",
    "countryName": "United States",
    "geographyId": "US-NY-36061",
    "peril": "WS",
    "occupancy": "Permanent",
    "occupancyGroup": "Com-Retail",
    "occupancySegment": "COMMERCIAL",
    "construction": "Steel",
    "yearBuilt": "Unknown",
    "distanceToCoast": "b=> 0 - 0.5 Miles from Coast",
    "geocodingQuality": "Coordinate",
    "numberOfStories": "4-7 stories",
    "building": 252000000.0,
    "contents": 126000000.0,
    "bi": 42000000.0,
    "tiv": 420000000,
    "explimGross": 336000000.0,
    "explimNet": 252000000.0,
    "locationCount": 1500,
    "accountCount": 115,
    "invalidTiv": null,
    "invalidCount": null,
    "currency": "USD",
    "exposureDataCutoffDate": "2023-09-30T00:00:00Z",
    "statecode": "NY",
    "stateName": "NEW YORK",
    "county": "36061",
    "countyName": "New York"
  }
]
